flask_rhoauth/__init__.py
flask_rhoauth/api_auth.py
flask_rhoauth/compat.py
flask_rhoauth/keycloak_admin.py
flask_rhoauth/openid.py
flask_rhoauth/utils/__init__.py
flask_rhoauth/utils/string.py
Flask_RhoAuth-2.2.0.dist-info/METADATA
Flask_RhoAuth-2.2.0.dist-info/WHEEL
Flask_RhoAuth-2.2.0.dist-info/top_level.txt
Flask_RhoAuth-2.2.0.dist-info/RECORD
